pynum2words/__init__.py
pynum2words/cli.py
pynum2words/dictionaries.py
pynum2words/dictionary_loader.py
pynum2words/pynum2words.py
pynum2words/dictionaries/afrikaans.n2w
pynum2words/dictionaries/amharic.n2w
pynum2words/dictionaries/arabic.n2w
pynum2words/dictionaries/armenian.n2w
pynum2words/dictionaries/bengali.n2w
pynum2words/dictionaries/chinese.n2w
pynum2words/dictionaries/dutch.n2w
pynum2words/dictionaries/english.n2w
pynum2words/dictionaries/finnish.n2w
pynum2words/dictionaries/french.n2w
pynum2words/dictionaries/german.n2w
pynum2words/dictionaries/greek.n2w
pynum2words/dictionaries/hebrew.n2w
pynum2words/dictionaries/hindi.n2w
pynum2words/dictionaries/hungarian.n2w
pynum2words/dictionaries/italian.n2w
pynum2words/dictionaries/japanese.n2w
pynum2words/dictionaries/kannada.n2w
pynum2words/dictionaries/korean.n2w
pynum2words/dictionaries/malay.n2w
pynum2words/dictionaries/oromo.n2w
pynum2words/dictionaries/persian.n2w
pynum2words/dictionaries/portuguese.n2w
pynum2words/dictionaries/romanian.n2w
pynum2words/dictionaries/russian.n2w
pynum2words/dictionaries/spanish.n2w
pynum2words/dictionaries/swahili.n2w
pynum2words/dictionaries/thai.n2w
pynum2words/dictionaries/tigrinya.n2w
pynum2words/dictionaries/turkish.n2w
pynum2words/dictionaries/ukrainian.n2w
pynum2words/dictionaries/urdu.n2w
pynum2words/dictionaries/vietnamese.n2w
pynum2words/dictionaries/zulu.n2w
pynum2words-1.4.0.dist-info/licenses/LICENSE
pynum2words-1.4.0.dist-info/METADATA
pynum2words-1.4.0.dist-info/WHEEL
pynum2words-1.4.0.dist-info/entry_points.txt
pynum2words-1.4.0.dist-info/top_level.txt
pynum2words-1.4.0.dist-info/RECORD
