Metadata-Version: 2.4
Name: pynum2words
Version: 1.4.0
Summary: pynum2words is a python library for converting numbers to their word representation and vice versa using a built-in or custom dictionary.
Author-email: BirukBelihu <birukbelihu1995@email.com>
License: Apache-2.0
Project-URL: Homepage, https://github.com/birukbelihu/pynum2words
Project-URL: Source, https://github.com/birukbelihu/pynum2words
Project-URL: Issues, https://github.com/birukbelihu/pynum2words/issues
Classifier: Programming Language :: Python :: 3.9
Classifier: Programming Language :: Python :: 3.10
Classifier: Programming Language :: Python :: 3.11
Classifier: Programming Language :: Python :: 3.12
Classifier: Programming Language :: Python :: 3.13
Requires-Python: >=3.9
License-File: LICENSE
Requires-Dist: pyglowx
Dynamic: license-file
